setup.cfg
setup.py
elasticsearch_cli.egg-info/PKG-INFO
elasticsearch_cli.egg-info/SOURCES.txt
elasticsearch_cli.egg-info/dependency_links.txt
elasticsearch_cli.egg-info/entry_points.txt
elasticsearch_cli.egg-info/requires.txt
elasticsearch_cli.egg-info/top_level.txt
source/__init__.py
source/config.py
source/es_connect.py
source/api/__init__.py
source/api/allocation/__init__.py
source/api/allocation/allocation.py
source/api/cluster/__init__.py
source/api/cluster/cluster.py
source/api/indices/__init__.py
source/api/indices/indices.py
source/api/info/__init__.py
source/api/info/info.py
source/api/master/__init__.py
source/api/master/master.py
source/api/nodes/__init__.py
source/api/nodes/nodes.py
source/api/settings/__init__.py
source/api/settings/settings.py
source/api/shards/__init__.py
source/api/shards/shards.py
source/api/templates/__init__.py
source/api/templates/templates.py
source/libs/__init__.py
source/libs/format_validator/__init__.py
source/libs/format_validator/format.py
source/libs/format_validator/test_format.py
source/libs/get_color/__init__.py
source/libs/get_color/get_color.py
source/libs/get_color/test_get_color.py
source/libs/get_heart/__init__.py
source/libs/get_heart/get_heart.py
source/libs/get_heart/test_get_heart.py
source/libs/name_validator/__init__.py
source/libs/name_validator/name_valid.py
source/libs/name_validator/test_name.py
source/libs/status_validator/__init__.py
source/libs/status_validator/status.py
source/libs/status_validator/test_format.py
source/libs/timeout_validator/__init__.py
source/libs/timeout_validator/test_timeout_parser.py
source/libs/timeout_validator/timeout.py