Metadata-Version: 1.1
Name: elasticsearch-cli
Version: 1.0.2
Summary: Elasticsearch cli
Home-page: https://github.com/WeslyG/elasticsearch-cli
Author: Wesly Allan
Author-email: weslyg22@gmail.com
License: MIT
Platform: UNKNOWN
Classifier: Programming Language :: Python :: Implementation
Classifier: Natural Language :: English
Classifier: License :: OSI Approved :: MIT License
Classifier: Operating System :: OS Independent
